setup.py
GBdistributions_ML/Binomialdistribution.py
GBdistributions_ML/Gaussiandistribution.py
GBdistributions_ML/Generaldistribution.py
GBdistributions_ML/__init__.py
GBdistributions_ML.egg-info/PKG-INFO
GBdistributions_ML.egg-info/SOURCES.txt
GBdistributions_ML.egg-info/dependency_links.txt
GBdistributions_ML.egg-info/not-zip-safe
GBdistributions_ML.egg-info/top_level.txt